schedulo_api-4.0.0.data/data/assets/API_RESPONSE_FORMATS.md
schedulo_api-4.0.0.data/data/assets/carleton/courses.json
schedulo_api-4.0.0.data/data/assets/uottawa/courses.json
schedulo_api-4.0.0.dist-info/licenses/COPYING
schedulo_api-4.0.0.dist-info/licenses/COPYING.LESSER
uoapi/__init__.py
uoapi/__modules__
uoapi/__version__.py
uoapi/log_config.py
uoapi/py.typed
uoapi/carleton/__init__.py
uoapi/carleton/discovery.py
uoapi/carleton/models.py
uoapi/core/__init__.py
uoapi/core/exceptions.py
uoapi/core/interfaces.py
uoapi/core/models.py
uoapi/course/__init__.py
uoapi/course/course_info.py
uoapi/course/models.py
uoapi/course/parse.py
uoapi/course/patterns.py
uoapi/course/prereq.py
uoapi/course/utils.py
uoapi/discovery/__init__.py
uoapi/discovery/discovery_service.py
uoapi/interfaces/__init__.py
uoapi/interfaces/api/__init__.py
uoapi/interfaces/api/app.py
uoapi/rmp/__init__.py
uoapi/rmp/rate_my_prof.py
uoapi/server/__init__.py
uoapi/server/app.py
uoapi/server/cli.py
uoapi/services/__init__.py
uoapi/services/course_service.py
uoapi/services/discovery_service.py
uoapi/services/rating_service.py
uoapi/services/timetable_service.py
uoapi/timetable/__init__.py
uoapi/timetable/query_timetable.py
uoapi/timetable/data/template_query.json
uoapi/universities/__init__.py
uoapi/universities/base.py
uoapi/universities/carleton/__init__.py
uoapi/universities/carleton/programs.py
uoapi/universities/carleton/provider.py
uoapi/universities/uottawa/__init__.py
uoapi/universities/uottawa/programs.py
uoapi/universities/uottawa/provider.py
uoapi/utils/__init__.py
uoapi/utils/config.py
uoapi/utils/patterns.py
schedulo_api-4.0.0.dist-info/METADATA
schedulo_api-4.0.0.dist-info/WHEEL
schedulo_api-4.0.0.dist-info/entry_points.txt
schedulo_api-4.0.0.dist-info/top_level.txt
schedulo_api-4.0.0.dist-info/RECORD
