Metadata-Version: 2.4
Name: schedulo-api
Version: 4.0.0
Summary: An API for retrieving public data from the University of Ottawa and Carleton University.
Home-page: https://github.com/Rain6435/uoapi
Author: Mohammed Elhasnaoui
Author-email: Mohammed Elhasnaoui <brosimo@outlook.fr>
Maintainer-email: Mohammed Elhasnaoui <brosimo@outlook.fr>
License: LGPL-3.0-or-later
Project-URL: Homepage, https://github.com/Rain6435/uoapi
Project-URL: Repository, https://github.com/Rain6435/uoapi
Project-URL: Issues, https://github.com/Rain6435/uoapi/issues
Project-URL: Documentation, https://github.com/Rain6435/uoapi#readme
Project-URL: Source Code, https://github.com/Rain6435/uoapi
Project-URL: Bug Reports, https://github.com/Rain6435/uoapi/issues
Project-URL: Release Notes, https://github.com/Rain6435/uoapi/releases
Keywords: university,ottawa,carleton,courses,api,scraping,education
Classifier: Development Status :: 5 - Production/Stable
Classifier: Environment :: Web Environment
Classifier: Intended Audience :: Education
Classifier: License :: OSI Approved :: GNU Lesser General Public License v3 or later (LGPLv3+)
Classifier: Natural Language :: English
Classifier: Natural Language :: French
Classifier: Operating System :: Microsoft :: Windows
Classifier: Operating System :: POSIX
Classifier: Programming Language :: Python
Classifier: Programming Language :: Python :: 3
Classifier: Programming Language :: Python :: 3.10
Classifier: Programming Language :: Python :: 3.11
Classifier: Programming Language :: Python :: 3.12
Classifier: Programming Language :: Python :: Implementation :: CPython
Classifier: Topic :: Education
Classifier: Topic :: Internet :: WWW/HTTP :: Indexing/Search
Requires-Python: >=3.10.0
License-File: COPYING
License-File: COPYING.LESSER
Requires-Dist: requests
Requires-Dist: regex
Requires-Dist: bs4
Requires-Dist: lxml
Requires-Dist: pandas
Requires-Dist: parsedatetime
Requires-Dist: pydantic
Requires-Dist: fastapi
Requires-Dist: uvicorn[standard]
Provides-Extra: tests
Requires-Dist: pytest; extra == "tests"
Requires-Dist: pytest-cov; extra == "tests"
Requires-Dist: httmock; extra == "tests"
Requires-Dist: mypy; extra == "tests"
Requires-Dist: flake8; extra == "tests"
Requires-Dist: black; extra == "tests"
Requires-Dist: bandit; extra == "tests"
Requires-Dist: types-requests; extra == "tests"
Dynamic: author
Dynamic: home-page
Dynamic: license-file
Dynamic: requires-python
